LICENSE
MANIFEST.in
README.rst
buildout.cfg
develop.cfg
pyproject.toml
requirements.txt
setup.py
version.txt
bob/__init__.py
bob.ip.base.egg-info/PKG-INFO
bob.ip.base.egg-info/SOURCES.txt
bob.ip.base.egg-info/dependency_links.txt
bob.ip.base.egg-info/not-zip-safe
bob.ip.base.egg-info/requires.txt
bob.ip.base.egg-info/top_level.txt
bob/ip/__init__.py
bob/ip/base/__functions__.py
bob/ip/base/__glcm__.py
bob/ip/base/__init__.py
bob/ip/base/affine.cpp
bob/ip/base/auxiliary.cpp
bob/ip/base/dct_features.cpp
bob/ip/base/face_eyes_norm.cpp
bob/ip/base/filter.cpp
bob/ip/base/gaussian.cpp
bob/ip/base/geom_norm.cpp
bob/ip/base/glcm.cpp
bob/ip/base/hog.cpp
bob/ip/base/lbp.cpp
bob/ip/base/lbp_top.cpp
bob/ip/base/main.cpp
bob/ip/base/main.h
bob/ip/base/tan_triggs.cpp
bob/ip/base/version.cpp
bob/ip/base/weighted_gaussian.cpp
bob/ip/base/cpp/Affine.cpp
bob/ip/base/cpp/DCTFeatures.cpp
bob/ip/base/cpp/FaceEyesNorm.cpp
bob/ip/base/cpp/GLCM.cpp
bob/ip/base/cpp/Gaussian.cpp
bob/ip/base/cpp/GeomNorm.cpp
bob/ip/base/cpp/HOG.cpp
bob/ip/base/cpp/LBP.cpp
bob/ip/base/cpp/LBPTop.cpp
bob/ip/base/cpp/TanTriggs.cpp
bob/ip/base/cpp/WeightedGaussian.cpp
bob/ip/base/data/LBP.hdf5
bob/ip/base/data/image.hdf5
bob/ip/base/data/affine/image_r10.hdf5
bob/ip/base/data/affine/image_r10_face_eyes_norm.hdf5
bob/ip/base/data/affine/image_r10_geom_norm.hdf5
bob/ip/base/data/affine/image_r70.hdf5
bob/ip/base/data/affine/image_r70_geom_norm.hdf5
bob/ip/base/data/affine/image_r70_mask.hdf5
bob/ip/base/data/filter/image_Gaussian.hdf5
bob/ip/base/data/filter/image_WeightedGaussian.hdf5
bob/ip/base/data/histo/image_histo.hdf5
bob/ip/base/data/histo/input_float.hdf5
bob/ip/base/data/histo/input_float.histo.hdf5
bob/ip/base/data/histo/input_int32.hdf5
bob/ip/base/data/histo/input_int32.histo.hdf5
bob/ip/base/data/histo/input_uint16.hdf5
bob/ip/base/data/histo/input_uint16.histo.hdf5
bob/ip/base/data/preprocessing/image_tantriggs.hdf5
bob/ip/base/data/preprocessing/image_tantriggs_MATLABREF.hdf5
bob/ip/base/include/bob.ip.base/Affine.h
bob/ip/base/include/bob.ip.base/Block.h
bob/ip/base/include/bob.ip.base/DCTFeatures.h
bob/ip/base/include/bob.ip.base/FaceEyesNorm.h
bob/ip/base/include/bob.ip.base/GLCM.h
